coopr.sucasa-3.0-py2.7-nspkg.pth
coopr/sucasa/__init__.py
coopr/sucasa/ampl_info.py
coopr/sucasa/ampl_parser.py
coopr/sucasa/main_script.py
coopr/sucasa/mapfile_parser.py
coopr/sucasa/run_ampl.py
coopr/sucasa/sucasa_PICO.py
coopr/sucasa/symb_info.py
coopr/sucasa/tests/__init__.py
coopr/sucasa/tests/models/__init__.py
coopr/sucasa/tests/models/test_amplbook2.py
coopr/sucasa/tests/unit/__init__.py
coopr/sucasa/tests/unit/test_AmplInfo.py
coopr/sucasa/tests/unit/test_parser.py
coopr/sucasa/tests/unit/test_symb_info.py
coopr.sucasa-3.0.dist-info/DESCRIPTION.rst
coopr.sucasa-3.0.dist-info/METADATA
coopr.sucasa-3.0.dist-info/metadata.json
coopr.sucasa-3.0.dist-info/namespace_packages.txt
coopr.sucasa-3.0.dist-info/RECORD
coopr.sucasa-3.0.dist-info/top_level.txt
coopr.sucasa-3.0.dist-info/WHEEL
